bip32/__init__.py
bip32/base58.py
bip32/bip32.py
bip32/ripemd160.py
bip32/utils.py
bip32-5.0.0.dist-info/licenses/LICENCE
bip32-5.0.0.dist-info/METADATA
bip32-5.0.0.dist-info/WHEEL
bip32-5.0.0.dist-info/top_level.txt
bip32-5.0.0.dist-info/RECORD
