Metadata-Version: 2.4
Name: bip32
Version: 5.0.0
Summary: Minimalistic implementation of BIP32 (Bitcoin HD wallets)
Author-email: Antoine Poinsot <darosior@protonmail.com>
Maintainer-email: Antoine Poinsot <darosior@protonmail.com>
License-Expression: BSD-3-Clause
Project-URL: Homepage, https://github.com/darosior/python-bip32
Project-URL: Repository, https://github.com/darosior/python-bip32
Project-URL: Issues, https://github.com/darosior/python-bip32/issues
Project-URL: Bug Tracker, https://github.com/darosior/python-bip32/issues
Project-URL: Changelog, https://github.com/darosior/python-bip32/tree/master/CHANGELOG.md
Keywords: bitcoin,key derivation,HD wallet
Classifier: Programming Language :: Python :: 3
Classifier: Operating System :: OS Independent
Classifier: Topic :: Security :: Cryptography
Requires-Python: >=3.9
License-File: LICENCE
Requires-Dist: coincurve<21,>=15.0
Dynamic: license-file
